whitespace_correction/__init__.py
whitespace_correction/model.py
whitespace_correction/version.py
whitespace_correction/api/__init__.py
whitespace_correction/api/cli.py
whitespace_correction/api/corrector.py
whitespace_correction/api/server.py
whitespace_correction/api/train.py
whitespace_correction-0.2.3.dist-info/licenses/LICENSE
whitespace_correction-0.2.3.dist-info/METADATA
whitespace_correction-0.2.3.dist-info/WHEEL
whitespace_correction-0.2.3.dist-info/entry_points.txt
whitespace_correction-0.2.3.dist-info/top_level.txt
whitespace_correction-0.2.3.dist-info/RECORD
