Metadata-Version: 2.4
Name: whitespace_correction
Version: 0.2.3
Summary: Correct missing or spurious whitespaces in text.
Author-email: Sebastian Walter <swalter@cs.uni-freiburg.de>
License:                                  Apache License
Project-URL: Github, https://github.com/ad-freiburg/whitespace-correction
Project-URL: Website, https://whitespace-correction.cs.uni-freiburg.de
Keywords: nlp,text,correction,whitespace
Classifier: Programming Language :: Python :: 3
Classifier: Topic :: Scientific/Engineering :: Artificial Intelligence
Classifier: Topic :: Software Development :: Libraries
Classifier: Topic :: Text Processing
Classifier: Topic :: Utilities
Requires-Python: >=3.8
License-File: LICENSE
Requires-Dist: dtpu==0.2.4
Requires-Dist: transformers>=4.26.0
Dynamic: license-file
